esm2quinox/__init__.py
esm2quinox/_custom_types.py
esm2quinox/_esm2.py
esm2quinox/_layer.py
esm2quinox/_torch2eqx.py
esm2quinox-0.2.0.dist-info/METADATA
esm2quinox-0.2.0.dist-info/WHEEL
esm2quinox-0.2.0.dist-info/licenses/LICENSE
esm2quinox-0.2.0.dist-info/RECORD
