Metadata-Version: 2.4
Name: esm2quinox
Version: 0.2.0
Summary: ESM2 implemented in Equinox+JAX.
Project-URL: repository, https://github.com/patrick-kidger/esm2quinox
Author-email: Patrick Kidger <contact@kidger.site>
License:                                  Apache License
License-File: LICENSE
Keywords: deep-learning,equinox,esm2,jax,neural-networks,protein-language-model
Classifier: Development Status :: 3 - Alpha
Classifier: Intended Audience :: Developers
Classifier: Intended Audience :: Financial and Insurance Industry
Classifier: Intended Audience :: Information Technology
Classifier: Intended Audience :: Science/Research
Classifier: License :: OSI Approved :: Apache Software License
Classifier: Natural Language :: English
Classifier: Programming Language :: Python :: 3
Classifier: Topic :: Scientific/Engineering :: Artificial Intelligence
Classifier: Topic :: Scientific/Engineering :: Information Analysis
Classifier: Topic :: Scientific/Engineering :: Mathematics
Requires-Python: >=3.10
Requires-Dist: equinox>=0.11.11
Requires-Dist: jax>=0.5.0
Requires-Dist: jaxtyping>=0.2.37
Provides-Extra: dev
Requires-Dist: beartype; extra == 'dev'
Requires-Dist: fair-esm==2.0.0; extra == 'dev'
Requires-Dist: pre-commit; extra == 'dev'
Requires-Dist: pytest; extra == 'dev'
Requires-Dist: torch; extra == 'dev'
